swiftapi/__init__.py
swiftapi/client.py
swiftapi/enforcement.py
swiftapi/exceptions.py
swiftapi/utils.py
swiftapi/verifier.py
swiftapi_python-1.0.3.dist-info/METADATA
swiftapi_python-1.0.3.dist-info/WHEEL
swiftapi_python-1.0.3.dist-info/top_level.txt
swiftapi_python-1.0.3.dist-info/RECORD
