Metadata-Version: 2.4
Name: swiftapi-python
Version: 1.0.3
Summary: SwiftAPI Python SDK - AI Action Verification Gateway
Author-email: Rayan Pal <rayan@swiftapi.ai>
License-Expression: MIT
Project-URL: Homepage, https://swiftapi.ai
Project-URL: Documentation, https://getswiftapi.com/docs
Keywords: swiftapi,ai,verification,attestation,security,governance,enforcement
Classifier: Development Status :: 4 - Beta
Classifier: Intended Audience :: Developers
Classifier: Operating System :: OS Independent
Classifier: Programming Language :: Python :: 3
Classifier: Programming Language :: Python :: 3.9
Classifier: Programming Language :: Python :: 3.10
Classifier: Programming Language :: Python :: 3.11
Classifier: Programming Language :: Python :: 3.12
Classifier: Topic :: Security
Classifier: Topic :: Software Development :: Libraries :: Python Modules
Requires-Python: >=3.9
Requires-Dist: requests>=2.31.0
Requires-Dist: pynacl>=1.5.0
Requires-Dist: colorama>=0.4.6
Provides-Extra: dev
Requires-Dist: pytest>=7.0.0; extra == "dev"
Requires-Dist: pytest-cov>=4.0.0; extra == "dev"
Requires-Dist: black>=23.0.0; extra == "dev"
Requires-Dist: mypy>=1.0.0; extra == "dev"
Requires-Dist: types-requests>=2.31.0; extra == "dev"
